hubmap_entity_sdk/__init__.py
hubmap_entity_sdk/_base_client.py
hubmap_entity_sdk/_client.py
hubmap_entity_sdk/_compat.py
hubmap_entity_sdk/_constants.py
hubmap_entity_sdk/_exceptions.py
hubmap_entity_sdk/_files.py
hubmap_entity_sdk/_models.py
hubmap_entity_sdk/_qs.py
hubmap_entity_sdk/_resource.py
hubmap_entity_sdk/_response.py
hubmap_entity_sdk/_streaming.py
hubmap_entity_sdk/_types.py
hubmap_entity_sdk/_version.py
hubmap_entity_sdk/py.typed
hubmap_entity_sdk/_utils/__init__.py
hubmap_entity_sdk/_utils/_compat.py
hubmap_entity_sdk/_utils/_datetime_parse.py
hubmap_entity_sdk/_utils/_logs.py
hubmap_entity_sdk/_utils/_proxy.py
hubmap_entity_sdk/_utils/_reflection.py
hubmap_entity_sdk/_utils/_resources_proxy.py
hubmap_entity_sdk/_utils/_streams.py
hubmap_entity_sdk/_utils/_sync.py
hubmap_entity_sdk/_utils/_transform.py
hubmap_entity_sdk/_utils/_typing.py
hubmap_entity_sdk/_utils/_utils.py
hubmap_entity_sdk/lib/.keep
hubmap_entity_sdk/resources/__init__.py
hubmap_entity_sdk/resources/ancestors.py
hubmap_entity_sdk/resources/children.py
hubmap_entity_sdk/resources/datasets.py
hubmap_entity_sdk/resources/descendants.py
hubmap_entity_sdk/resources/doi.py
hubmap_entity_sdk/resources/entity_types_all.py
hubmap_entity_sdk/resources/parents.py
hubmap_entity_sdk/resources/uploads.py
hubmap_entity_sdk/resources/entities/__init__.py
hubmap_entity_sdk/resources/entities/entities.py
hubmap_entity_sdk/resources/entities/type.py
hubmap_entity_sdk/types/__init__.py
hubmap_entity_sdk/types/ancestor_retrieve_response.py
hubmap_entity_sdk/types/child_retrieve_response.py
hubmap_entity_sdk/types/dataset_bulk_update_params.py
hubmap_entity_sdk/types/dataset_bulk_update_response.py
hubmap_entity_sdk/types/dataset_create_components_params.py
hubmap_entity_sdk/types/dataset_create_components_response.py
hubmap_entity_sdk/types/dataset_list_donors_response.py
hubmap_entity_sdk/types/dataset_list_organs_response.py
hubmap_entity_sdk/types/dataset_list_revisions_params.py
hubmap_entity_sdk-2.0.0a46.dist-info/METADATA
hubmap_entity_sdk-2.0.0a46.dist-info/WHEEL
hubmap_entity_sdk-2.0.0a46.dist-info/licenses/LICENSE
hubmap_entity_sdk-2.0.0a46.dist-info/RECORD
